CHANGES.txt
LICENSE.txt
MANIFEST.in
README
setup.py
provpy/__init__.py
provpy.egg-info/PKG-INFO
provpy.egg-info/SOURCES.txt
provpy.egg-info/dependency_links.txt
provpy.egg-info/top_level.txt
provpy/model/README.txt
provpy/model/TODO.txt
provpy/model/__init__.py
provpy/model/core.py
provpy/model/examples/__init__.py
provpy/model/examples/provpyexample.py
provpy/model/examples/provpyexample_Account.py
provpy/model/examples/provpyexample_Elements.py
provpy/model/examples/provpyexample_Literal.py
provpy/model/examples/provpyexample_Qname_Namespace.py
provpy/model/examples/provpyexample_Relations.py
provpy/model/test/__init__.py
provpy/model/test/testexample.py
provpy/model/test/testtest.py