Metadata-Version: 1.0
Name: provpy
Version: 1.0.0
Summary: A Python implementation of PROV-DM data model.
Home-page: http://github.com/trungdong/w3-prov/tree/master/provpy
Author: Huanjia Yang
Author-email: huanjiayang@hotmail.com
License: LICENSE.txt
Platform: UNKNOWN
